{
  "probe_acc": "G07695ZT",
  "dp":  "10",
  "related_glycans": [ 
   {
     "accession": "G03216SJ",
     "relative_dp": "-1",
     "match": "9"
   },
   {
     "accession": "G05948HK",
     "relative_dp": "+0",
     "match": "10"
   },
   {
     "accession": "G07695ZT",
     "relative_dp": "+0",
     "match": "10"
   },
   {
     "accession": "G20894MY",
     "relative_dp": "-1",
     "match": "9"
   },
   {
     "accession": "G24329OK",
     "relative_dp": "+0",
     "match": "10"
   },
   {
     "accession": "G27874QL",
     "relative_dp": "-1",
     "match": "9"
   },
   {
     "accession": "G45187EI",
     "relative_dp": "+1",
     "match": "10"
   },
   {
     "accession": "G45997JW",
     "relative_dp": "+1",
     "match": "10"
   },
   {
     "accession": "G58517TJ",
     "relative_dp": "+1",
     "match": "10"
   }
  ]
}