{
  "probe_acc": "G08520NM",
  "dp":  "8",
  "related_glycans": [ 
   {
     "accession": "G00028MO",
     "relative_dp": "-1",
     "match": "7"
   },
   {
     "accession": "G01999JH",
     "relative_dp": "+0",
     "match": "8"
   },
   {
     "accession": "G02945KQ",
     "relative_dp": "+1",
     "match": "8"
   },
   {
     "accession": "G03605BS",
     "relative_dp": "+1",
     "match": "8"
   },
   {
     "accession": "G03652TR",
     "relative_dp": "-1",
     "match": "7"
   },
   {
     "accession": "G04445KN",
     "relative_dp": "-1",
     "match": "7"
   },
   {
     "accession": "G05763EW",
     "relative_dp": "+1",
     "match": "8"
   },
   {
     "accession": "G08520NM",
     "relative_dp": "+0",
     "match": "8"
   },
   {
     "accession": "G12504XV",
     "relative_dp": "+1",
     "match": "8"
   },
   {
     "accession": "G13151XE",
     "relative_dp": "+1",
     "match": "8"
   },
   {
     "accession": "G13974DV",
     "relative_dp": "-1",
     "match": "7"
   },
   {
     "accession": "G15732HH",
     "relative_dp": "+1",
     "match": "8"
   },
   {
     "accession": "G16828VN",
     "relative_dp": "+1",
     "match": "8"
   },
   {
     "accession": "G17336FF",
     "relative_dp": "-1",
     "match": "7"
   },
   {
     "accession": "G19841IT",
     "relative_dp": "+1",
     "match": "8"
   },
   {
     "accession": "G20173ZW",
     "relative_dp": "+1",
     "match": "8"
   },
   {
     "accession": "G20966TZ",
     "relative_dp": "+1",
     "match": "8"
   },
   {
     "accession": "G24674CB",
     "relative_dp": "+1",
     "match": "8"
   },
   {
     "accession": "G28355WG",
     "relative_dp": "+1",
     "match": "8"
   },
   {
     "accession": "G30588SI",
     "relative_dp": "+1",
     "match": "8"
   },
   {
     "accession": "G37841NF",
     "relative_dp": "-1",
     "match": "7"
   },
   {
     "accession": "G38297TU",
     "relative_dp": "+0",
     "match": "8"
   },
   {
     "accession": "G44747CU",
     "relative_dp": "+1",
     "match": "8"
   },
   {
     "accession": "G47179RN",
     "relative_dp": "-1",
     "match": "7"
   },
   {
     "accession": "G48148UW",
     "relative_dp": "+1",
     "match": "8"
   },
   {
     "accession": "G48405LH",
     "relative_dp": "+1",
     "match": "8"
   },
   {
     "accession": "G50730KL",
     "relative_dp": "+1",
     "match": "8"
   },
   {
     "accession": "G53168IY",
     "relative_dp": "-1",
     "match": "7"
   },
   {
     "accession": "G55220VL",
     "relative_dp": "-1",
     "match": "7"
   },
   {
     "accession": "G58214IQ",
     "relative_dp": "-1",
     "match": "7"
   },
   {
     "accession": "G60875XB",
     "relative_dp": "+1",
     "match": "8"
   },
   {
     "accession": "G65893EZ",
     "relative_dp": "+1",
     "match": "8"
   },
   {
     "accession": "G67924FL",
     "relative_dp": "+1",
     "match": "8"
   },
   {
     "accession": "G71470CO",
     "relative_dp": "+1",
     "match": "8"
   },
   {
     "accession": "G75896PD",
     "relative_dp": "-1",
     "match": "7"
   },
   {
     "accession": "G78341DP",
     "relative_dp": "+0",
     "match": "8"
   },
   {
     "accession": "G82233UN",
     "relative_dp": "+1",
     "match": "8"
   },
   {
     "accession": "G82942ZJ",
     "relative_dp": "+1",
     "match": "8"
   },
   {
     "accession": "G84064AY",
     "relative_dp": "+1",
     "match": "8"
   },
   {
     "accession": "G88329BN",
     "relative_dp": "+0",
     "match": "8"
   },
   {
     "accession": "G93060PS",
     "relative_dp": "+1",
     "match": "8"
   },
   {
     "accession": "G98602UY",
     "relative_dp": "+1",
     "match": "8"
   }
  ]
}