{
  "probe_acc": "G10578GY",
  "dp":  "16",
  "related_glycans": [ 
   {
     "accession": "G10470SE",
     "relative_dp": "+1",
     "match": "16"
   },
   {
     "accession": "G10578GY",
     "relative_dp": "+0",
     "match": "16"
   },
   {
     "accession": "G17155VX",
     "relative_dp": "+0",
     "match": "16"
   },
   {
     "accession": "G24816DA",
     "relative_dp": "+1",
     "match": "16"
   },
   {
     "accession": "G49305IN",
     "relative_dp": "+1",
     "match": "16"
   },
   {
     "accession": "G50462VS",
     "relative_dp": "+1",
     "match": "16"
   },
   {
     "accession": "G50489VC",
     "relative_dp": "+1",
     "match": "16"
   },
   {
     "accession": "G53234IR",
     "relative_dp": "+1",
     "match": "16"
   },
   {
     "accession": "G82864KM",
     "relative_dp": "+0",
     "match": "16"
   },
   {
     "accession": "G86696LV",
     "relative_dp": "+1",
     "match": "16"
   },
   {
     "accession": "G99568AR",
     "relative_dp": "+1",
     "match": "16"
   }
  ]
}