{
  "probe_acc": "G11588II",
  "dp":  "10",
  "related_glycans": [ 
   {
     "accession": "G00279YF",
     "relative_dp": "-1",
     "match": "9"
   },
   {
     "accession": "G01010HW",
     "relative_dp": "-1",
     "match": "9"
   },
   {
     "accession": "G11588II",
     "relative_dp": "+0",
     "match": "10"
   },
   {
     "accession": "G29434RB",
     "relative_dp": "-1",
     "match": "9"
   },
   {
     "accession": "G54884LT",
     "relative_dp": "-1",
     "match": "9"
   },
   {
     "accession": "G61312PU",
     "relative_dp": "+1",
     "match": "10"
   },
   {
     "accession": "G61553DD",
     "relative_dp": "-1",
     "match": "9"
   }
  ]
}