{
  "probe_acc": "G14996IQ",
  "dp":  "8",
  "related_glycans": [ 
   {
     "accession": "G00978TF",
     "relative_dp": "-1",
     "match": "7"
   },
   {
     "accession": "G05319BS",
     "relative_dp": "+1",
     "match": "8"
   },
   {
     "accession": "G14996IQ",
     "relative_dp": "+0",
     "match": "8"
   },
   {
     "accession": "G15204IM",
     "relative_dp": "+1",
     "match": "8"
   },
   {
     "accession": "G16201LW",
     "relative_dp": "+1",
     "match": "8"
   },
   {
     "accession": "G16759KR",
     "relative_dp": "+1",
     "match": "8"
   },
   {
     "accession": "G21005TQ",
     "relative_dp": "+0",
     "match": "8"
   },
   {
     "accession": "G24517QL",
     "relative_dp": "+1",
     "match": "8"
   },
   {
     "accession": "G38362AS",
     "relative_dp": "+0",
     "match": "8"
   },
   {
     "accession": "G43255OW",
     "relative_dp": "+1",
     "match": "8"
   },
   {
     "accession": "G48954CA",
     "relative_dp": "+1",
     "match": "8"
   },
   {
     "accession": "G53962WT",
     "relative_dp": "+1",
     "match": "8"
   },
   {
     "accession": "G67719WQ",
     "relative_dp": "+1",
     "match": "8"
   },
   {
     "accession": "G69411IG",
     "relative_dp": "-1",
     "match": "7"
   },
   {
     "accession": "G83393GK",
     "relative_dp": "+1",
     "match": "8"
   },
   {
     "accession": "G84542XB",
     "relative_dp": "+1",
     "match": "8"
   },
   {
     "accession": "G86386QT",
     "relative_dp": "-1",
     "match": "7"
   },
   {
     "accession": "G94297FY",
     "relative_dp": "+1",
     "match": "8"
   },
   {
     "accession": "G96122UB",
     "relative_dp": "+1",
     "match": "8"
   },
   {
     "accession": "G97575FW",
     "relative_dp": "+1",
     "match": "8"
   }
  ]
}