{
  "probe_acc": "G19541IU",
  "dp":  "20",
  "related_glycans": [ 
   {
     "accession": "G03754YM",
     "relative_dp": "+1",
     "match": "20"
   },
   {
     "accession": "G19541IU",
     "relative_dp": "+0",
     "match": "20"
   },
   {
     "accession": "G40027VO",
     "relative_dp": "-1",
     "match": "19"
   },
   {
     "accession": "G44515AZ",
     "relative_dp": "-1",
     "match": "19"
   },
   {
     "accession": "G49053WC",
     "relative_dp": "+0",
     "match": "20"
   },
   {
     "accession": "G66106WQ",
     "relative_dp": "+1",
     "match": "20"
   },
   {
     "accession": "G74859XI",
     "relative_dp": "+0",
     "match": "20"
   },
   {
     "accession": "G82201IZ",
     "relative_dp": "-1",
     "match": "19"
   },
   {
     "accession": "G90784AP",
     "relative_dp": "-1",
     "match": "19"
   },
   {
     "accession": "G95251MI",
     "relative_dp": "-1",
     "match": "19"
   }
  ]
}