{
  "probe_acc": "G48277OH",
  "dp":  "14",
  "related_glycans": [ 
   {
     "accession": "G46425HN",
     "relative_dp": "+1",
     "match": "14"
   },
   {
     "accession": "G19726AG",
     "relative_dp": "-1",
     "match": "13"
   },
   {
     "accession": "G51941IR",
     "relative_dp": "+1",
     "match": "14"
   },
   {
     "accession": "G19053XS",
     "relative_dp": "-1",
     "match": "13"
   },
   {
     "accession": "G13091NP",
     "relative_dp": "-1",
     "match": "13"
   },
   {
     "accession": "G48277OH",
     "relative_dp": "+0",
     "match": "14"
   }
  ]
}