{
  "probe_acc": "G54380FJ",
  "dp":  "10",
  "related_glycans": [ 
   {
     "accession": "G05319BS",
     "relative_dp": "-1",
     "match": "9"
   },
   {
     "accession": "G16759KR",
     "relative_dp": "-1",
     "match": "9"
   },
   {
     "accession": "G33685ZQ",
     "relative_dp": "+1",
     "match": "10"
   },
   {
     "accession": "G43255OW",
     "relative_dp": "-1",
     "match": "9"
   },
   {
     "accession": "G46185ND",
     "relative_dp": "+1",
     "match": "10"
   },
   {
     "accession": "G47816DI",
     "relative_dp": "+1",
     "match": "10"
   },
   {
     "accession": "G48954CA",
     "relative_dp": "-1",
     "match": "9"
   },
   {
     "accession": "G53582JE",
     "relative_dp": "-1",
     "match": "9"
   },
   {
     "accession": "G53752TA",
     "relative_dp": "+1",
     "match": "10"
   },
   {
     "accession": "G54380FJ",
     "relative_dp": "+0",
     "match": "10"
   },
   {
     "accession": "G58667NI",
     "relative_dp": "-1",
     "match": "9"
   },
   {
     "accession": "G67719WQ",
     "relative_dp": "-1",
     "match": "9"
   },
   {
     "accession": "G68937TM",
     "relative_dp": "+0",
     "match": "10"
   },
   {
     "accession": "G74837KH",
     "relative_dp": "-1",
     "match": "9"
   },
   {
     "accession": "G79368CP",
     "relative_dp": "+1",
     "match": "10"
   },
   {
     "accession": "G83022ZQ",
     "relative_dp": "+1",
     "match": "10"
   },
   {
     "accession": "G84542XB",
     "relative_dp": "-1",
     "match": "9"
   },
   {
     "accession": "G96122UB",
     "relative_dp": "-1",
     "match": "9"
   }
  ]
}