{
  "probe_acc": "G56271TF",
  "dp":  "8",
  "related_glycans": [ 
   {
     "accession": "G04048YA",
     "relative_dp": "-1",
     "match": "7"
   },
   {
     "accession": "G19106CR",
     "relative_dp": "+0",
     "match": "8"
   },
   {
     "accession": "G23647WB",
     "relative_dp": "+1",
     "match": "8"
   },
   {
     "accession": "G30553WH",
     "relative_dp": "+1",
     "match": "8"
   },
   {
     "accession": "G34394KR",
     "relative_dp": "+1",
     "match": "8"
   },
   {
     "accession": "G39437XQ",
     "relative_dp": "+1",
     "match": "8"
   },
   {
     "accession": "G47206MY",
     "relative_dp": "+1",
     "match": "8"
   },
   {
     "accession": "G47407FC",
     "relative_dp": "+1",
     "match": "8"
   },
   {
     "accession": "G56271TF",
     "relative_dp": "+0",
     "match": "8"
   },
   {
     "accession": "G59741XZ",
     "relative_dp": "-1",
     "match": "7"
   },
   {
     "accession": "G85891FA",
     "relative_dp": "+1",
     "match": "8"
   },
   {
     "accession": "G93310KW",
     "relative_dp": "-1",
     "match": "7"
   },
   {
     "accession": "G98117HW",
     "relative_dp": "+1",
     "match": "8"
   },
   {
     "accession": "G99897FQ",
     "relative_dp": "+1",
     "match": "8"
   }
  ]
}