{
  "probe_acc": "G57565TQ",
  "dp":  "13",
  "related_glycans": [ 
   {
     "accession": "G12222NC",
     "relative_dp": "+1",
     "match": "13"
   },
   {
     "accession": "G36533LR",
     "relative_dp": "+0",
     "match": "13"
   },
   {
     "accession": "G41455NO",
     "relative_dp": "+1",
     "match": "13"
   },
   {
     "accession": "G47007PV",
     "relative_dp": "+1",
     "match": "13"
   },
   {
     "accession": "G57565TQ",
     "relative_dp": "+0",
     "match": "13"
   },
   {
     "accession": "G77915NM",
     "relative_dp": "+1",
     "match": "13"
   }
  ]
}