{
  "probe_acc": "G60692DB",
  "dp":  "7",
  "related_glycans": [ 
   {
     "accession": "G09362PR",
     "relative_dp": "-1",
     "match": "6"
   },
   {
     "accession": "G10182XZ",
     "relative_dp": "+0",
     "match": "7"
   },
   {
     "accession": "G10197JO",
     "relative_dp": "+1",
     "match": "7"
   },
   {
     "accession": "G10209QU",
     "relative_dp": "+1",
     "match": "7"
   },
   {
     "accession": "G21311PN",
     "relative_dp": "+1",
     "match": "7"
   },
   {
     "accession": "G25744PP",
     "relative_dp": "+1",
     "match": "7"
   },
   {
     "accession": "G30585MP",
     "relative_dp": "+1",
     "match": "7"
   },
   {
     "accession": "G42680EX",
     "relative_dp": "-1",
     "match": "6"
   },
   {
     "accession": "G56737NO",
     "relative_dp": "+1",
     "match": "7"
   },
   {
     "accession": "G60692DB",
     "relative_dp": "+0",
     "match": "7"
   },
   {
     "accession": "G61751GZ",
     "relative_dp": "-1",
     "match": "6"
   },
   {
     "accession": "G63411NB",
     "relative_dp": "-1",
     "match": "6"
   },
   {
     "accession": "G70073SG",
     "relative_dp": "-1",
     "match": "6"
   },
   {
     "accession": "G79348ZY",
     "relative_dp": "+1",
     "match": "7"
   },
   {
     "accession": "G86309VR",
     "relative_dp": "+0",
     "match": "7"
   },
   {
     "accession": "G93986UQ",
     "relative_dp": "+0",
     "match": "7"
   }
  ]
}