{
  "probe_acc": "G82320NZ",
  "dp":  "11",
  "related_glycans": [ 
   {
     "accession": "G02679YX",
     "relative_dp": "+1",
     "match": "11"
   },
   {
     "accession": "G05478GN",
     "relative_dp": "+0",
     "match": "11"
   },
   {
     "accession": "G11010AN",
     "relative_dp": "+1",
     "match": "11"
   },
   {
     "accession": "G13537KO",
     "relative_dp": "+1",
     "match": "11"
   },
   {
     "accession": "G29109PM",
     "relative_dp": "+0",
     "match": "11"
   },
   {
     "accession": "G51472TJ",
     "relative_dp": "+1",
     "match": "11"
   },
   {
     "accession": "G63208BT",
     "relative_dp": "+1",
     "match": "11"
   },
   {
     "accession": "G67767BR",
     "relative_dp": "+1",
     "match": "11"
   },
   {
     "accession": "G76646HT",
     "relative_dp": "+1",
     "match": "11"
   },
   {
     "accession": "G82320NZ",
     "relative_dp": "+0",
     "match": "11"
   },
   {
     "accession": "G87908HE",
     "relative_dp": "+1",
     "match": "11"
   }
  ]
}