{
  "probe_acc": "G86601RH",
  "dp":  "6",
  "related_glycans": [ 
   {
     "accession": "G00026MO",
     "relative_dp": "-1",
     "match": "5"
   },
   {
     "accession": "G20624LQ",
     "relative_dp": "-1",
     "match": "5"
   },
   {
     "accession": "G22768VO",
     "relative_dp": "-1",
     "match": "5"
   },
   {
     "accession": "G34749PQ",
     "relative_dp": "-1",
     "match": "5"
   },
   {
     "accession": "G36400RA",
     "relative_dp": "+1",
     "match": "6"
   },
   {
     "accession": "G43547MI",
     "relative_dp": "-1",
     "match": "5"
   },
   {
     "accession": "G62167DK",
     "relative_dp": "-1",
     "match": "5"
   },
   {
     "accession": "G66875SM",
     "relative_dp": "-1",
     "match": "5"
   },
   {
     "accession": "G86601RH",
     "relative_dp": "+0",
     "match": "6"
   },
   {
     "accession": "G94600JO",
     "relative_dp": "+1",
     "match": "6"
   },
   {
     "accession": "G97547WF",
     "relative_dp": "-1",
     "match": "5"
   },
   {
     "accession": "G99519QZ",
     "relative_dp": "+1",
     "match": "6"
   }
  ]
}