{
  "probe_acc": "G96024GG",
  "dp":  "11",
  "related_glycans": [ 
   {
     "accession": "G48369JO",
     "relative_dp": "-1",
     "match": "10"
   },
   {
     "accession": "G85200FA",
     "relative_dp": "+1",
     "match": "11"
   },
   {
     "accession": "G61702UX",
     "relative_dp": "+1",
     "match": "11"
   },
   {
     "accession": "G86385RC",
     "relative_dp": "-1",
     "match": "10"
   },
   {
     "accession": "G96024GG",
     "relative_dp": "+0",
     "match": "11"
   },
   {
     "accession": "G40702WU",
     "relative_dp": "-1",
     "match": "10"
   },
   {
     "accession": "G55786MG",
     "relative_dp": "-1",
     "match": "10"
   }
  ]
}